scapy_p0f/__init__.py
scapy_p0f/base_classes.py
scapy_p0f/consts.py
scapy_p0f/p0fv3.py
scapy_p0f/utils.py
scapy_p0f/data/p0f.fp
scapy_p0f-1.0.5.dist-info/LICENSE
scapy_p0f-1.0.5.dist-info/METADATA
scapy_p0f-1.0.5.dist-info/WHEEL
scapy_p0f-1.0.5.dist-info/top_level.txt
scapy_p0f-1.0.5.dist-info/RECORD
