Metadata-Version: 2.1
Name: scapy-p0f
Version: 1.0.5
Summary: p0f v3 clone written in Python
Home-page: https://github.com/Nisitay/scapy-p0f
Author: Itay Margolin
Author-email: itay62848@gmail.com
License: MIT
Download-URL: https://github.com/Nisitay/scapy-p0f/tarball/master
Keywords: p0f,scapy,network,packets
Platform: UNKNOWN
Classifier: Development Status :: 4 - Beta
Classifier: License :: OSI Approved :: MIT License
Classifier: Environment :: Console
Classifier: Programming Language :: Python
Classifier: Programming Language :: Python :: 2
Classifier: Programming Language :: Python :: 2.7
Classifier: Programming Language :: Python :: 3
Classifier: Programming Language :: Python :: 3.4
Classifier: Programming Language :: Python :: 3.5
Classifier: Programming Language :: Python :: 3.6
Classifier: Programming Language :: Python :: 3.7
Classifier: Topic :: Security
Classifier: Topic :: System :: Networking
Classifier: Topic :: Software Development :: Libraries :: Python Modules
Requires-Python: >=2.7, !=3.0.*, !=3.1.*, !=3.2.*, !=3.3.*, <4
Requires-Dist: scapy
